LICENSE
MANIFEST.in
setup.cfg
setup.py
hanger51client/__init__.py
hanger51client.egg-info/PKG-INFO
hanger51client.egg-info/SOURCES.txt
hanger51client.egg-info/dependency_links.txt
hanger51client.egg-info/requires.txt
hanger51client.egg-info/top_level.txt