Metadata-Version: 1.1
Name: hanger51client
Version: 1.0.4
Summary: A client library for calling the Hanger51 API
Home-page: https://getme.co.uk
Author: David Bailey, Anthony Blackshaw
Author-email: david@getme.co.uk, ant@getme.co.uk
License: MIT
Keywords: hanger51
Platform: UNKNOWN
Classifier: Development Status :: 5 - Production/Stable
Classifier: Intended Audience :: Developers
Classifier: License :: OSI Approved :: MIT License
Classifier: Operating System :: MacOS :: MacOS X
Classifier: Operating System :: Microsoft :: Windows
Classifier: Operating System :: POSIX
Classifier: Programming Language :: Python :: 3.4
Classifier: Programming Language :: Python :: 3.5
